corrupt_o11y/__init__.py
corrupt_o11y/__meta__.py
corrupt_o11y/py.typed
corrupt_o11y/_internal/__init__.py
corrupt_o11y/_internal/dependencies.py
corrupt_o11y/_internal/env.py
corrupt_o11y/logging/__init__.py
corrupt_o11y/logging/collector.py
corrupt_o11y/logging/config.py
corrupt_o11y/logging/processors/__init__.py
corrupt_o11y/logging/processors/conditional.py
corrupt_o11y/logging/processors/exception.py
corrupt_o11y/logging/processors/field_filter.py
corrupt_o11y/logging/processors/opentelemetry.py
corrupt_o11y/logging/processors/pii.py
corrupt_o11y/logging/processors/safety.py
corrupt_o11y/logging/utils/__init__.py
corrupt_o11y/logging/utils/mute.py
corrupt_o11y/metadata/__init__.py
corrupt_o11y/metadata/service_info.py
corrupt_o11y/metrics/__init__.py
corrupt_o11y/metrics/collector.py
corrupt_o11y/metrics/config.py
corrupt_o11y/operational/__init__.py
corrupt_o11y/operational/config.py
corrupt_o11y/operational/server.py
corrupt_o11y/operational/status.py
corrupt_o11y/tracing/__init__.py
corrupt_o11y/tracing/config.py
corrupt_o11y/tracing/tracer.py
corrupt_o11y-0.3.1.dist-info/METADATA
corrupt_o11y-0.3.1.dist-info/WHEEL
corrupt_o11y-0.3.1.dist-info/licenses/LICENSE
corrupt_o11y-0.3.1.dist-info/RECORD
