Metadata-Version: 2.4
Name: corrupt-o11y
Version: 0.3.1
Summary: A comprehensive observability library for Python applications with logging, metrics, and tracing
Project-URL: Homepage, https://github.com/mykyta/corrupt-o11y-py
Project-URL: Documentation, https://github.com/mykyta/corrupt-o11y-py#readme
Project-URL: Repository, https://github.com/mykyta/corrupt-o11y-py.git
Project-URL: Bug Tracker, https://github.com/mykyta/corrupt-o11y-py/issues
Author-email: Mykyta <mykyta@example.com>
License: MIT
License-File: LICENSE
Keywords: logging,metrics,monitoring,observability,opentelemetry,prometheus,tracing
Classifier: Development Status :: 3 - Alpha
Classifier: Intended Audience :: Developers
Classifier: License :: OSI Approved :: MIT License
Classifier: Operating System :: OS Independent
Classifier: Programming Language :: Python :: 3
Classifier: Programming Language :: Python :: 3.11
Classifier: Programming Language :: Python :: 3.12
Classifier: Programming Language :: Python :: 3.13
Classifier: Topic :: Software Development :: Libraries :: Python Modules
Classifier: Topic :: System :: Logging
Classifier: Topic :: System :: Monitoring
Classifier: Topic :: System :: Systems Administration
Requires-Python: >=3.11
Requires-Dist: orjson>=3.8.0
Requires-Dist: prometheus-client>=0.20.0
Provides-Extra: all
Requires-Dist: aiohttp>=3.9.0; extra == 'all'
Requires-Dist: opentelemetry-api>=1.20.0; extra == 'all'
Requires-Dist: opentelemetry-exporter-otlp-proto-grpc>=1.20.0; extra == 'all'
Requires-Dist: opentelemetry-exporter-otlp-proto-http>=1.20.0; extra == 'all'
Requires-Dist: opentelemetry-sdk>=1.20.0; extra == 'all'
Requires-Dist: structlog>=23.3.0; extra == 'all'
Provides-Extra: logging
Requires-Dist: structlog>=23.3.0; extra == 'logging'
Provides-Extra: otlp
Requires-Dist: opentelemetry-api>=1.20.0; extra == 'otlp'
Requires-Dist: opentelemetry-sdk>=1.20.0; extra == 'otlp'
Provides-Extra: otlp-all
Requires-Dist: opentelemetry-api>=1.20.0; extra == 'otlp-all'
Requires-Dist: opentelemetry-exporter-otlp-proto-grpc>=1.20.0; extra == 'otlp-all'
Requires-Dist: opentelemetry-exporter-otlp-proto-http>=1.20.0; extra == 'otlp-all'
Requires-Dist: opentelemetry-sdk>=1.20.0; extra == 'otlp-all'
Provides-Extra: otlp-grpc
Requires-Dist: opentelemetry-api>=1.20.0; extra == 'otlp-grpc'
Requires-Dist: opentelemetry-exporter-otlp-proto-grpc>=1.20.0; extra == 'otlp-grpc'
Requires-Dist: opentelemetry-sdk>=1.20.0; extra == 'otlp-grpc'
Provides-Extra: otlp-http
Requires-Dist: opentelemetry-api>=1.20.0; extra == 'otlp-http'
Requires-Dist: opentelemetry-exporter-otlp-proto-http>=1.20.0; extra == 'otlp-http'
Requires-Dist: opentelemetry-sdk>=1.20.0; extra == 'otlp-http'
Provides-Extra: server
Requires-Dist: aiohttp>=3.9.0; extra == 'server'
